rtl/spi_master.v
// =============================================================================
// Company:        Targeting RTL/VLSI Internships
// Engineer:       Your Name
// 
// Create Date:    2026
// Module Name:    spi_master
// Project Name:   SPI Controller Subsystem
// Target Devices: Synthesizable FPGAs / ASICs
// Description:    Core SPI Master supporting 8-bit transfers in SPI Mode 0 
//                 (CPOL = 0, CPHA = 0).
// =============================================================================

module spi_master (
    input  wire       clk,          // System Clock
    input  wire       rst_n,        // Asynchronous Active-Low Reset
    
    // User/System Interface
    input  wire [7:0] tx_data,      // Parallel Data to transmit
    input  wire       start,        // Kickstart transfer trigger
    output reg        ready,        // Transmitter is ready for new data
    output reg        done,         // Pulse indicating transfer completion
    output reg  [7:0] rx_data,      // Parallel Data received
    
    // SPI Physical Interface
    output reg        sclk,         // SPI Serial Clock
    output reg        mosi,         // Master Output Slave Input
    input  wire       miso,         // Master Input Slave Output
    output reg        cs_n          // Chip Select (Active Low)
);

    // Finite State Machine (FSM) States
    localparam IDLE   = 2'b00;
    localparam LEAD   = 2'b01; // Setup time before SCLK starts
    localparam TRAIL  = 2'b10; // Hold time after SCLK ends

    reg [1:0] state;
    reg [2:0] bit_cnt;         // Tracks 0 to 7 bits
    reg [7:0] shift_reg_tx;    // Internal TX Shift Register
    reg [7:0] shift_reg_rx;    // Internal RX Shift Register
    reg       sclk_en;         // Enables SCLK generation
    reg       clk_div;         // Simple toggle for SCLK generation (Sys_Clk / 2)

    // -------------------------------------------------------------------------
    // 1. Clock Generation (Simple Divider for Mode 0)
    // -------------------------------------------------------------------------
    always @(posedge clk or negedge rst_n) begin
        if (!rst_n) begin
            clk_div <= 1'b0;
        end else if (sclk_en) begin
            clk_div <= ~clk_div;
        end else begin
            clk_div <= 1'b0;
        end
    end

    // In Mode 0, SCLK is idle low.
    always @(*) begin
        sclk = clk_div;
    end

    // Detect internal SCLK edges for shifting and sampling
    wire sclk_rising  = (sclk_en && !clk_div &&  ~clk_div); // Lookahead for rising edge
    wire sclk_falling = (sclk_en &&  clk_div &&   clk_div); // Lookahead for falling edge

    // -------------------------------------------------------------------------
    // 2. Core FSM and Control Logic
    // -------------------------------------------------------------------------
    always @(posedge clk or negedge rst_n) begin
        if (!rst_n) begin
            state        <= IDLE;
            ready        <= 1'b1;
            done         <= 1'b0;
            cs_n         <= 1'b1;
            sclk_en      <= 1'b0;
            bit_cnt      <= 3'd0;
            shift_reg_tx <= 8'h00;
            shift_reg_rx <= 8'h00;
            rx_data      <= 8'h00;
            mosi         <= 1'b0;
        end else begin
            done <= 1'b0; // Default pulse

            case (state)
                IDLE: begin
                    ready <= 1'b1;
                    cs_n  <= 1'b1;
                    mosi  <= 1'b0;
                    if (start) begin
                        ready        <= 1'b0;
                        cs_n         <= 1'b0;
                        shift_reg_tx <= tx_data;
                        state        <= LEAD;
                    end
                end

                LEAD: begin
                    // Drive first MSB bit right away (Mode 0 setup)
                    mosi    <= shift_reg_tx[7];
                    sclk_en <= 1'b1;
                    
                    // Synchronize state transition with the clock generation
                    if (clk_div == 1'b1) begin 
                        bit_cnt <= 3'd7;
                        state   <= TRAIL;
                    end
                end

                TRAIL: begin
                    // Mode 0: Sample MISO on Rising Edge
                    if (sclk_en && !clk_div) begin 
                        shift_reg_rx <= {shift_reg_rx[6:0], miso};
                    end
                    
                    // Mode 0: Shift/Drive MOSI on Falling Edge
                    if (sclk_en && clk_div) begin
                        if (bit_cnt == 3'd0) begin
                            sclk_en <= 1'b0;
                            cs_n    <= 1'b1;
                            done    <= 1'b1;
                            rx_data <= {shift_reg_rx[6:0], miso}; // Capture final bit
                            state   <= IDLE;
                        end else begin
                            bit_cnt      <= bit_cnt - 1'b1;
                            shift_reg_tx <= {shift_reg_tx[6:0], 1'b0};
                            mosi         <= shift_reg_tx[6]; 
                        end
                    end
                end

                default: state <= IDLE;
            endcase
        end
    end

endmodule

tb/spi_tb.v


// Create Date:    2026
// Module Name:    spi_tb
// Project Name:   SPI Controller Subsystem
// Description:    Basic Testbench for testing Phase 1 Core SPI Master (Mode 0).
// =============================================================================

`timescale 1ns / 1ps

module spi_tb;

    // Testbench Signals
    reg        clk;
    reg        rst_n;
    reg  [7:0] tx_data;
    reg        start;
    wire       ready;
    wire       done;
    wire [7:0] rx_data;
    wire       sclk;
    wire       mosi;
    reg        miso;
    wire       cs_n;

    // Instantiate the Device Under Test (DUT)
    spi_master uut (
        .clk     (clk),
        .rst_n   (rst_n),
        .tx_data (tx_data),
        .start   (start),
        .ready   (ready),
        .done    (done),
        .rx_data (rx_data),
        .sclk    (sclk),
        .mosi    (mosi),
        .miso    (miso),
        .cs_n    (cs_n)
    );

    // 1. Clock Generation: 50 MHz clock (Period = 20ns)
    always begin
        #10 clk = ~clk;
    end

    // 2. Stimulus Generation
    initial begin
        // Setup waveform dumping for GTKWave/EDA Playground
        $dumpfile("waveforms/spi_trace.vcd");
        $dumpvars(0, spi_tb);

        // Initialize inputs
        clk     = 1'b0;
        rst_n   = 1'b0;
        tx_data = 8'h00;
        start   = 1'b0;
        miso    = 1'b0;

        // Apply Reset for 40ns
        #40;
        rst_n = 1'b1;
        #20;

        // Wait until master is ready
        wait(ready == 1'b1);
        #10;

        // Transaction 1: Send Data 8'hA5 (Binary: 10100101)
        tx_data = 8'hA5; 
        start   = 1'b1;   // Assert start pulse
        #20;
        start   = 1'b0;   // Deassert start pulse

        // Simulating incoming MISO data from a slave device
        // We change MISO on falling edges of SCLK so Master can safely sample on rising edges.
        @(negedge sclk) miso = 1'b1; // bit 7
        @(negedge sclk) miso = 1'b0; // bit 6
        @(negedge sclk) miso = 1'b1; // bit 5
        @(negedge sclk) miso = 1'b1; // bit 4
        @(negedge sclk) miso = 1'b0; // bit 3
        @(negedge sclk) miso = 1'b0; // bit 2
        @(negedge sclk) miso = 1'b1; // bit 1
        @(negedge sclk) miso = 1'b0; // bit 0 (Final sample)

        // Wait for the Master to complete the transfer
        @(posedge done);
        #40;

        $display("[TB SUCCESS] Transfer completed. Received Data: %h", rx_data);
        $finish;
    end

endmodule

waveforms/spi_trace.vcd
$date
	Wed Jun 03 16:10:54 2026
$end
$version
	Icarus Verilog
$end
$timescale
	1ps
$end
$scope module spi_tb $end
$var wire 1 ! sclk $end
$var wire 8 " rx_data [7:0] $end
$var wire 1 # ready $end
$var wire 1 $ mosi $end
$var wire 1 % done $end
$var wire 1 & cs_n $end
$var reg 1 ' clk $end
$var reg 1 ( miso $end
$var reg 1 ) rst_n $end
$var reg 1 * start $end
$var reg 8 + tx_data [7:0] $end
$scope module uut $end
$var wire 1 ' clk $end
$var wire 1 ( miso $end
$var wire 1 ) rst_n $end
$var wire 1 , sclk_falling $end
$var wire 1 - sclk_rising $end
$var wire 1 * start $end
$var wire 8 . tx_data [7:0] $end
$var parameter 2 / IDLE $end
$var parameter 2 0 LEAD $end
$var parameter 2 1 TRAIL $end
$var reg 3 2 bit_cnt [2:0] $end
$var reg 1 3 clk_div $end
$var reg 1 & cs_n $end
$var reg 1 % done $end
$var reg 1 $ mosi $end
$var reg 1 # ready $end
$var reg 8 4 rx_data [7:0] $end
$var reg 1 ! sclk $end
$var reg 1 5 sclk_en $end
$var reg 8 6 shift_reg_rx [7:0] $end
$var reg 8 7 shift_reg_tx [7:0] $end
$var reg 2 8 state [1:0] $end
$upscope $end
$upscope $end
$enddefinitions $end
$comment Show the parameter values. $end
$dumpall
b10 1
b1 0
b0 /
$end
#0
$dumpvars
b0 8
b0 7
b0 6
05
b0 4
03
b0 2
b0 .
0-
0,
b0 +
0*
0)
0(
0'
1&
0%
0$
1#
b0 "
0!
$end
#10000
1'
#20000
0'
#30000
1'
#40000
0'
1)
#50000
1'
#60000
0'
#70000
b1 8
b10100101 7
0&
0#
1'
1*
b10100101 +
b10100101 .
#80000
0'
#90000
1-
15
1$
1'
0*
#100000
0'
#110000
0-
1!
1,
13
1'
#120000
0'
#130000
1(
1-
0!
0,
b10 8
b111 2
03
1'
#140000
0'
#150000
0-
1!
1,
13
b1 6
1'
#160000
0'
#170000
0(
1-
0!
0,
0$
b1001010 7
b110 2
03
1'
#180000
0'
#190000
0-
1!
1,
13
b10 6
1'
#200000
0'
#210000
1(
1-
0!
0,
1$
b10010100 7
b101 2
03
1'
#220000
0'
#230000
0-
1!
1,
13
b101 6
1'
#240000
0'
#250000
1-
0!
0,
0$
b101000 7
b100 2
03
1'
#260000
0'
#270000
0-
1!
1,
13
b1011 6
1'
#280000
0'
#290000
0(
1-
0!
0,
b1010000 7
b11 2
03
1'
#300000
0'
#310000
0-
1!
1,
13
b10110 6
1'
#320000
0'
#330000
1-
0!
0,
1$
b10100000 7
b10 2
03
1'
#340000
0'
#350000
0-
1!
1,
13
b101100 6
1'
#360000
0'
#370000
1(
1-
0!
0,
0$
b1000000 7
b1 2
03
1'
#380000
0'
#390000
0-
1!
1,
13
b1011001 6
1'
#400000
0'
#410000
0(
1-
0!
0,
1$
b10000000 7
b0 2
03
1'
#420000
0'
#430000
0-
1!
1,
13
b10110010 6
1'
#440000
0'
#450000
0!
0,
b0 8
b1100100 "
b1100100 4
1%
1&
05
03
1'
#460000
0'
#470000
0$
1#
0%
1'
